{
  "301": "Primary Bath Amenities: 5-Pc Bath, Ceramic Tile, Double Vanity, Natural Wood, Spa Shower, Tub",
  "685": "SqFt Source:",
  "1201": "Total Full Bth:Total 3/4 Bth:Total 1/2 Bth:",
  "1997": "Const Status:",
  "24 hour\n\t\t\t\t\t\ttoday\n\t\t\t\t\t\t3 day\n\t\t\t\t\t\t7 day": "Refresh",
  "refresh": "Customize",
  "customize": "Default Search\n\t\t\t\t\t\t\t\t\t\t\t\t\n\t\t\t\t\t\t\t\t\t\t\t\t\n\t\t\t\t\t\t\t\t\t\t\t\t\t\nPreviousNext\n· 1 of 3\n\t\t\t\t\t\t\t\t\t\t\t\t\n\t\t\t\t\t\t\t\t\t\t\t\t\n\t\t\t\t\t\t\t\t\t\t\t\t\t of \n\t\t\t\t\t\t\t\t\t\t\t\t\n\t\t\t\t\t\t\t\t\t\t\t\t\n\t\t\t\t\t\t\t\t\t\t\t\t\tChecked 0\n\t\t\t\t\t\t\t\t\t\t\t\t\t\t\t\t\t\t\t\t\t\t\t\t\n\t\t\t\t\t\t\t\t\t\t\t\t\n\t\t\t\t\t\t\t\t\t\t\t\t\tAll\n\t\t\t\t\t\t\t\t\t\t\t\t\t·\n\t\t\t\t\t\t\t\t\t\t\t\t\tNone\n\t\t\t\t\t\t\t\t\t\t\t\t\t·\n\t\t\t\t\t\t\t\t\t\t\t\t\tPage\n\t\t\t\t\t\t\t\t\t\t\t\t\tPage\n\t\t\t\t\t\t\t\t\t\t\t\t\t·\n\t\t\t\t\t\t\t\t\t\t\t\t\n\t\t\t\t\t\t\t\t\t\t\t\t\n\t\t\t\t\t\t\t\t\t\t\t\t\n\t\t\t\t\t\t\t\t\t\t\t\t\t\n\t\t\t\t\t\t\t\t\t\t\t\t\t\t\n\t\t\t\t\t\t\t\t\t\t\t\t\t\t\t\n\t\t\t\t\t\t\t\t\t\t\t\t\t\t\t\t\n\t\t\t\t\t\t\t\t\t\t\t\t\t\t\t\n\t\t\t\t\t\t\t\t\t\t\t\t\t\t\t\n\t\t\t\t\t\t\t\t\t\t\t\t\t\t\t\t\n\t\t\t\t\t\t\t\t\t\t\t\t\t\t\t\n\t\t\t\t\t\t\t\t\t\t\t\t\t\t\t \t\t\t\t\t\t\t\t\t\t\t\n\t\t\t\t\t\t\t\t\t\t\t\t\t\t\n\t\t\t\t\t\t\t\t\t\t\t\t\t\n\t\t\t\t\t\t\t\t\t\t\t\t\n\t\t\t\t\t\t\t\t\t\t\t\t\n\t\t\t\t\t\t\t\t\t\t\t\t\tComp View display\n\t\t\t\t\t\t\t\t\t\t\t\t\n\t\t\t\t\t\t\t\t\t\t\t\n\t\t\t\t\t\t\t\t\t\t\n\t\t\t\t\t\t\t\t\t\n\t\t\t\t\t\t\t\t\t\n\t\t\t\t\t\t\t\t\t\n\t\t\t\t\t\t\t\t\t\t\n\t\t\t\t\t\t\t\t\t\t\t\n\t\t\t\t\t\t\t\t\t\t\t\t\n\t\t\t\t\t\t\t\t\t\t\t\t\n\t\t\t\t\t\t\t\t\t\t\t\t\tDisplay\n\n\t\tmy:Single Line\n\t\tmy:Copy of Single Line\n\t\tmy:Schools\n\t\tmy:Comp View\n\t\tmy:Copy of Single Line\n\t\tmy:Relocation Comp View\n\t\tSingle Line\n\t\t360 Property View\n\t\tThumbnail\n\t\tShort\n\t\tHotsheet\n\t\tAgent Report Preview\n\t\tAppraisal Report (Res only)\n\t\tAgent Full Report/Map\n\t\tAgent Full Report w/photos\n\t\tAgent Full Report (Condensed)\n\t\tPhoto Gallery\n\t\tThumbnail Gallery w/Remarks\n\t\tCustomer Single Line\n\t\tCustomer Mobile\n\t\tCustomer Preview\n\t\tCustomer Short\n\t\tCustomer Full Report\n\t\tCustomer Full Report /Map\n\t\tCustomer Full Report w/photos\n\t\tCustomer Full Report (Condensed)\n\n\t\n\nat\n\n\t\t1\n\n\t\nper page\n\n\n\t\t\t\t\t\t\t\t\t\t\t\t\n\t\t\t\t\t\t\t\t\t\t\t\t\n\t\t\t\t\t\t\t\t\t\t\t\t\n\t\t\t\t\t\t\t\t\t\t\t\t\t\n\t\t\t\t\t\t\t\t\t\t\t\t\n\t\t\t\t\t\t\t\t\t\t\t\t\n\t\t\t\t\t\t\t\t\t\t\t\t\t\n\t\t\t\t\t\t\t\t\t\t\t\t\t\n\t\t\t\t\t\t\t\t\t\t\t\t\n\t\t\t\t\t\t\t\t\t\t\t\t\n\t\t\t\t\t\t\t\t\t\t\t\t\t\n\t\t\t\t\t\t\t\t\t\t\t\t\n\t\t\t\t\t\t\t\t\t\t\t\t\n\t\t\t\t\t\t\t\t\t\t\t\t\t\n\t\t\t\t\t\t\t\t\t\t\t\t\n\t\t\t\t\t\t\t\t\t\t\t\t\n\t\t\t\t\t\t\t\t\t\t\t\t\t\n\t\t\t\t\t\t\t\t\t\t\t\t\n\t\t\t\t\t\t\t\t\t\t\t\t\n\t\t\t\t\t\t\t\t\t\t\t\t\t\n\t\t\t\t\t\t\t\t\t\t\t\t\n\t\t\t\t\t\t\t\t\t\t\t\t\n\t\t\t\t\t\t\t\t\t\t\t\t\t\n\t\t\t\t\t\t\t\t\t\t\t\t\n\t\t\t\t\t\t\t\t\t\t\t\t\n\t\t\t\t\t\t\t\t\t\t\t\t\t\n\t\t\t\t\t\t\t\t\t\t\t\t\n\t\t\t\t\t\t\t\t\t\t\t\t\n\t\t\t\t\t\t\t\t\t\t\t\t\t\n\t\t\t\t\t\t\t\t\t\t\t\t\n\t\t\t\t\t\t\t\t\t\t\t\n\t\t\t\t\t\t\t\t\t\t\n\t\t\t\t\t\t\t\t\t\n\t\t\t\t\t\t\t\t\t\n\t\t\t\t\t\t\t\t\t\n\t\t\t\t\t\t\t\t\t\t\n\t\t\t\t\t\t\t\t\t\t\n\t\t\t\t\t\t\t\t\t\t\t\n\t\t\t\t\t\t\t\t\t\t\t\t\n\n\t\n\t\t\n\t\n\t\n\t\n\t\n\t\t<div class=\"list\" style=\"display:block;\">\n\t\t\t<span class=\"\">Did you mean:</span>\n\t\t</div>\n\t\n\t\n\t\t<div class=\"list\" style=\"display:block;\">\n\t\t\tYour exact location could not be determined.\n\t\t\t<a class=\"go\" href=\"#\">Use approximate location</a>\n\t\t\t<a class=\"cancel\" href=\"#\">Cancel</a>\n\t\t</div>\n\t\n\t\n\t\t<div class=\"list\" style=\"display:block;\">\n\t\t\tNo matching address in MLS boundaries.\n\t\t\t<a class=\"cancel\" href=\"#\">Close</a>\n\t\t</div>\n\t\n\t\n\t\tMy Current Location",
  "default search": "PreviousNext\n· 1 of 3",
  "previousnext\n· 1 of 3": "of",
  "checked 0": "All\n\t\t\t\t\t\t\t\t\t\t\t\t\t·\n\t\t\t\t\t\t\t\t\t\t\t\t\tNone\n\t\t\t\t\t\t\t\t\t\t\t\t\t·\n\t\t\t\t\t\t\t\t\t\t\t\t\tPage\n\t\t\t\t\t\t\t\t\t\t\t\t\tPage\n\t\t\t\t\t\t\t\t\t\t\t\t\t·",
  "comp view display": "Display\n\n\t\tmy:Single Line\n\t\tmy:Copy of Single Line\n\t\tmy:Schools\n\t\tmy:Comp View\n\t\tmy:Copy of Single Line\n\t\tmy:Relocation Comp View\n\t\tSingle Line\n\t\t360 Property View\n\t\tThumbnail\n\t\tShort\n\t\tHotsheet\n\t\tAgent Report Preview\n\t\tAppraisal Report (Res only)\n\t\tAgent Full Report/Map\n\t\tAgent Full Report w/photos\n\t\tAgent Full Report (Condensed)\n\t\tPhoto Gallery\n\t\tThumbnail Gallery w/Remarks\n\t\tCustomer Single Line\n\t\tCustomer Mobile\n\t\tCustomer Preview\n\t\tCustomer Short\n\t\tCustomer Full Report\n\t\tCustomer Full Report /Map\n\t\tCustomer Full Report w/photos\n\t\tCustomer Full Report (Condensed)\n\n\t\n\nat\n\n\t\t1\n\n\t\nper page",
  "agent full report/map": "RESIDENTIAL-Single Family-Detached",
  "move left": "→",
  "move right": "↑",
  "move up": "↓",
  "move down": "+",
  "zoom in": "-",
  "zoom out": "Home",
  "home": "Jump left by 75%",
  "jump left by 75%": "End",
  "end": "Jump right by 75%",
  "jump right by 75%": "Page Up",
  "page up": "Jump up by 75%",
  "jump up by 75%": "Page Down",
  "page down": "Jump down by 75%",
  "directions/cross:": "From I-25 North, take exit 158/Baptist Rd, turn right on Baptist Rd, right on Highcrest Ln, right on Falcon Ridge Ct, home is on the right corner.",
  "school district:": "38-Lewis-Palmer",
  "38-lewis-palmer": "Grade School:",
  "taxes:": "$3,687",
  "$3,687": "Tax Year:",
  "tax year:": "2024",
  "covenants:": "Yes",
  "mgmt name:": "MSI",
  "hoa 1:": "The Ridge at Fox Run",
  "the ridge at fox run": "719-578-5610",
  "719-578-5610": "HOA 1 Dues: $250 Annual",
  "hoa 1 dues: $250 annual": "HOA 1 Dues Include:",
  "hoa 1 dues include:": "Covenant Enforcement, Management, Snow Removal",
  "metro district 1:": "DONALA",
  "donala": "719-488-3603",
  "719-488-3603": "Metro Dist 1 Dues: $0",
  "metro dist 1 dues: $0": "MetroDist1 Dues Incl:",
  "metrodist1 dues incl:": "Water",
  "water": "MetroDist1 Website:",
  "metrodist1 website:": "https://www.donalawater.org/",
  "community features:": "Hiking or Biking Trails, Parks or Open Space",
  "square feet": "Year Built:",
  "year built:": "1997",
  "const status:": "Existing Home",
  "existing home": "Est. Comp Date:",
  "total sqft:": "4,250",
  "4,250": "Unit Desc:",
  "floor plan:": "2 Story",
  "2 story": "Builder Name:",
  "finished sqft:": "4,250",
  "above grade sqft:": "2,511",
  "2,511": "Structure:",
  "structure:": "Framed on Lot, Wood Frame",
  "upper sqft:": "685",
  "sqft source:": "Assessor Records",
  "main sqft:": "1,826",
  "1,826": "Outbuildings:",
  "basement sqft:": "1,739",
  "1,739": "Basement/Foundation: Full Basement",
  "% basement finished:": "100",
  "gar (parking) #:": "2",
  "gar (parking) type: attached": "Garage Remotes:",
  "garage amenities:": "Even with Main Level",
  "baths": "Baths: 4",
  "bathroom (full):\nm": "Bathroom (Full):",
  "bathroom (full):": "B",
  "bathroom (full):\nu": "Bathroom (Full):",
  "bathroom (full):\nb": "Bathroom (Full):",
  "bathroom (1/2):\nm": "Bathroom (1/2):",
  "bathroom (1/2):": "M",
  "total full bth:total 3/4 bth:total 1/2 bth:": "301",
  "rooms": "Beds Total: 5",
  "main lvl bed: yes": "Main Beds: 1",
  "main beds: 1": "Upper Beds: 2",
  "upper beds: 2": "Lower Beds: 0",
  "lower beds: 0": "Basement Beds: 2",
  "bedroom - primary:": "M",
  "17x13": "Bath Adjoins, Walk-in Closet",
  "bath adjoins, walk-in closet": "Bedroom:\nB\n13x14\nCarpet",
  "bedroom:\nb\n13x14\ncarpet": "Bedroom:",
  "bedroom:": "U",
  "13x14": "Carpet",
  "carpet": "Dining Room:\nM\n16x14\nNatural Wood",
  "bedroom:\nb\n16x17\ncarpet": "Bedroom:",
  "16x17": "Carpet",
  "bedroom:\nu\n20x13\ncarpet": "Bedroom:",
  "20x13": "Carpet",
  "dining room:\nm\n16x14\nnatural wood": "Dining Room:",
  "dining room:": "M",
  "16x14": "Natural Wood",
  "natural wood": "Office:\nM\n13x12",
  "family room:\nb\n15x21\nwalk-out": "Family Room:",
  "family room:": "B",
  "15x21": "Walk-out",
  "walk-out": "Kitchen:\nM\n19x21\nCounter Top-Solid Surface, Eat-In/Country, Island, Natural Wood",
  "kitchen:": "M",
  "19x21": "Counter Top-Solid Surface, Eat-In/Country, Island, Natural Wood",
  "laundry space:\nb": "Laundry Space:",
  "laundry space:": "B",
  "living room:\nm\n15x19\nnatural wood": "Living Room:",
  "living room:": "M",
  "15x19": "Natural Wood",
  "office:\nm\n13x12": "Office:",
  "office:": "M",
  "other features": "Roofing:",
  "roofing:": "Composite Shingle",
  "composite shingle": "Window Type:",
  "window type:": "Vinyl",
  "siding:": "Fiber Cement",
  "fireplaces:": "Main Level, One",
  "misc. interior feat:": "5-Pc Bath, 9Ft + Ceilings, French Doors, Great Room, Vaulted Ceilings",
  "misc. items:": "High Speed Internet Avail., HOA Required $, Kitchen Pantry",
  "appliances:": "Cook Top, Dishwasher, Disposal, Double Oven, Microwave Oven, Refrigerator",
  "laundry facilities:": "Main",
  "exclusions:": "Sellers personal property, Locks (key pads and biometric), sensors and cameras.",
  "lot": "Legal Desc:",
  "legal desc:": "LOT 16 THE RIDGE AT FOX RUN FIL NO 1",
  "zoning:": "PUD",
  "pud": "Zoning Entity:",
  "acres:": "0.46",
  "0.46": "Lot Sqft:",
  "lot sqft:": "20,036",
  "lot location:": "Near Schools, Near Shopping Center",
  "lot desc:": "Corner, Cul-de-sac, Level, Trees/Woods",
  "street desc:": "County Road",
  "driveway:": "Concrete",
  "concrete": "Alley:",
  "alley:": "None",
  "fence:": "None",
  "none": "Landscape:",
  "landscape:": "All",
  "heating": "Forced Air",
  "cooling": "Ceiling Fan(s), Central Air",
  "existing water:": "Association/District",
  "sanitation:": "Septic",
  "existing utilities:": "Electricity Connected, Natural Gas Available",
  "property remarks": "Property Description Remarks:",
  "terms": "Terms Offered:",
  "terms offered:": "Cash, Conventional, FHA, VA",
  "cash, conventional, fha, va": "1st Right of Refusal:",
  "possession terms:": "DOD",
  "dod": "Possession Date:",
  "earnest money:": "$9000",
  "$9000": "Earnest Money Holder: Core Title",
  "earnest money holder: core title": "EM Promissory Note Accepted:",
  "title company:": "Core Title Group LLC",
  "core title group llc": "Title Evidence:",
  "assumable loan:": "No",
  "notices:": "Not Applicable",
  "contact/showing details": "Listing Office:",
  "listing office:": "RE/MAX Real Estate Group LLC",
  "office ph:": "719-534-7900",
  "office fax:": "719-594-4573",
  "listing agent:": "Jake Wade",
  "jake wade": "jakewadeteam@gmail.com",
  "listing agent ph:": "719-205-0372",
  "listing agent fax:": "719-594-4573",
  "co-list agent:": "Lorian Ducharme",
  "lorian ducharme": "lorian@prosalesproperties.com",
  "co-list agent ph:": "(719) 930-8622",
  "(719) 930-8622": "Co-List Agent Fax:",
  "photo: agr": "VOW: Yes",
  "vow: yes": "Elec Adv: Yes",
  "elec adv: yes": "Blog: Yes",
  "blog: yes": "AVM: Yes",
  "avm: yes": "Display Address: Yes",
  "display address: yes": "Virtually Staged: No",
  "occupied:": "Owner",
  "showing instructions:": "24 Hour Notice, Appointment Only",
  "24 hour notice, appointment only": "Key: Other Box",
  "appointment contact:": "ShowingTime",
  "show/agent remarks": "Interior and exterior cameras are in use. All Showings and Inspections must have a licensed agent present. Please remove shoes or wear booties, lock up, leave a card. Feedback is appreciated. Information provided is deemed reliable, but Buyer/Buyer Agent to verify for accuracy.",
  "sold information": "Buyer Office:",
  "buyer office:": "Lee and Associates Real Estate, Inc.",
  "buyer office ph:": "719-963-6032",
  "buyer office fax:": "719-963-6032",
  "buyer agent:": "Stephanie Lee MRP",
  "stephanie lee mrp": "leeassociatesre@gmail.com",
  "ba ph:": "719-466-0241",
  "719-466-0241": "BA Fax:",
  "ba fax:": "719-963-6032",
  "719-963-6032": "BA Add'l Ph:",
  "concessions $:": "$10,000",
  "$10,000": "Closing Costs:Property Improvement Costs:Financing Costs:Other Costs:",
  "sold terms:": "Conventional",
  "list date:": "09/23/25",
  "pending date:": "01/16/26",
  "01/16/26": "Under Contract Date:",
  "under contract date:": "01/16/26",
  "sold price: $815,000": "Sold Date:",
  "sold date:": "02/27/26",
  "02/27/26": "View Comparable Properties",
  "sp/lp:": "0.97",
  "0.97": "SP/SF:",
  "sp/sf:": "$192",
  "list price: $840,000": "Original List Price: $900,000",
  "original list price: $900,000": "DOM: 115",
  "dom: 115": "CDOM: 116",
  "cdom: 116": "MLS#: 1037416",
  "cancel": "Save",
  "criteria": "Email",
  "email": "Print",
  "print": "Share Link\n\t\t\t\t\t\t\t\t\n\n\n\t\n\n\n\t\n\t\t\n\t\t\t\n\t\t\t\t\n\t\t\t\t\n\t\t\t\t\t\n\t\t\t\t\t\n\t\t\t\t\t\t \n\t\t\t\t\t\t\n\t\t\t\t\t\t\tCreate share link for  listings\n\t\t\t\t\t\t\n\t\t\t\t\t\n\t\t\t\t\t\n\t\t\t\t\t\t\n\t\t\t\t\t\t\t\n\t\t\t\t\t\t\t\t\n\t\t\t\t\t\t\t\t\tListing Set Name:\n\t\t\t\t\t\t\t\t\t\t\t\t\t\n\t\t\t\t\t\t\t\t\n\t\t\t\t\t\t\t\t\t\n\t\t\t\t\t\t\t\t\t\t\n\t\t\t\t\t\t\t\n\t\t\t\t\t\t\n\t\t\t\t\t\n\t\t\t\t\t\n\t\t\t\t\t\t\n\t\t\t\t\t\t\t\n\t\t\t\t\t\t\t\t\n\t\t\t\t\t\t\t\t\tLink URL:\n\t\t\t\t\t\t\t\t\t\t\t\t\t\n\t\t\t\t\t\t\t\t\n\t\t\t\t\t\t\t\t\t\n\t\t\t\t\t\t\t\t\t\t\n\t\t\t\t\t\t\t\n\t\t\t\t\t\t\n\t\t\t\t\t\n\t\t\t\t\n\t\t\t\t\n\t\t\t\t\t\n\t\t\t\t\t\t\n\t\t\t\t\t\t\n\t\t\t\t\t\t\tCancel\n\t\t\t\t\t\t\n\t\t\t\t\t\t\n\t\t\t\t\t\t\tGenerate Link\n\t\t\t\t\t\t\n\t\t\n\t\t\t\t\t\t\n\t\t\t\t\t\t\tCopy URL",
  "generate link": "Copy URL",
  "cma": "Directions",
  "directions": "Stats",
  "stats": "Export",
  "export": "ShowingTime",
  "showingtime": "Quick CMA",
  "narrow": "Discard",
  "discard": "Sort",
  "new saved search": "New Auto Email",
  "new auto email": "New Speed Bar Shortcut",
  "remove checked": "Add to",
  "add to": "View",
  "view": "New Cart\n\t\t\t\n\n\n\t\n\n\n\t\n\t\t\n\t\t\t\n\t\t\t\t\n\t\t\t\t\n\t\t\t\t\t\n\t\t\t\t\t\n\t\t\t\t\t\t \n\t\t\t\t\t\t\n\t\t\t\t\t\t\tAdd/Edit Cart\n\t\t\t\t\t\t\n\t\t\t\t\t\n\t\t\t\t\t\n\t\t\t\t\t\t\n\t\t\t\t\t\t\t\n\t\t\t\t\t\t\t\t\n\t\t\t\t\t\t\t\t\tCart Name:\n\t\t\t\t\t\t\t\t\t\n\t\t\t\t\t\t\t\t\t\t\t\t\t\n\t\t\t\t\t\t\t\n\t\t\t\n\t\t\t\t\t\t\t\t\tContact:\n\t\t\t\t\t\t\t\t\n\t\t\t\n\t\t\t\t\t\t\t\t\t\n\t\t\n\t\t\t\n\t\t\t\n\t\t\t\n\t\t\t\t\n\t\t\t\tBaxter, Josh\n\t\t\t\tThomson, Ryan\n\t\t\t\t--- more (click) ---\n\n\t\t\t\n\t\t\t Create a New Contact\n\t\t\t\n\t\t\n\t\n\n\n\t\t\t\n\n\t\n\t\t\t\t\n\t\t\t\n\t\t\n\t\t\t\n\n\n\t\n\t\t\t\t\n\t\t\t\n\t\t\n\t\t\t\n\n\n\n\t\t\t\t\t\t\t\t\n\t\t\n\t\t\t\t\t\n\t\t\t\t\t\t\t\n\t\t\t\t\t\t\n\t\t\t\t\t\n\t\t\t\t\n\t\t\t\t\n\t\t\t\t\t\n\t\t\t\t\t\t\n\t\t\t\t\t\t\n\t\t\t\t\t\t\tCancel\n\t\t\t\t\t\t\n\t\t\t\t\t\t\n\t\t\t\t\t\t\tSave",
  "contact:": "Baxter, Josh\n\t\t\t\tThomson, Ryan\n\t\t\t\t--- more (click) ---\n\n\t\t\t\n\t\t\t Create a New Contact",
  "sold": "02/27/26",
  "county:": "El Paso",
  "status:": "Sold",
  "price:": "$815,000",
  "bed/bath:": "5",
  "gar/parking#:": "2",
  "tot sqft:": "4,250",
  "lp/sf:": "$198",
  "sub area:": "The Ridge At Fox Run",
  "dom:": "115",
  "cdom:": "116",
  "sched#:": "6129304016",
  "mls#:": "1037416",
  "mgmt phone:": "719-578-5610",
  "hoa 1 dues:": "$250",
  "metro dist 1 dues:": "$0",
  "est. comp date:": "",
  "builder name:": "",
  "builder model:": "",
  "basement/foundation:": "Full Basement",
  "patio/deck desc:": "Wood Deck",
  "gar (parking) type:": "Attached",
  "baths:": "4",
  "total upper bth:": "",
  "total main bth:": "",
  "total lower bth:": "",
  "total full bth:": "",
  "total 3/4 bth:": "",
  "primary bath amenities:": "5-Pc Bath, Ceramic Tile, Double Vanity, Natural Wood, Spa Shower, Tub",
  "beds total:": "5",
  "main lvl bed:": "Yes",
  "main beds:": "1",
  "upper beds:": "2",
  "lower beds:": "0",
  "basement beds:": "2",
  "earnest money holder:": "Core Title",
  "em promissory note accepted:": "",
  "listing agent add'l ph:": "",
  "co-list agent add'l ph:": "",
  "type agreement:": "ERS",
  "service level:": "Full Service",
  "photo:": "AGR",
  "vow:": "Yes",
  "elec adv:": "Yes",
  "blog:": "Yes",
  "avm:": "Yes",
  "display address:": "Yes",
  "virtually staged:": "No",
  "key:": "Other Box",
  "closing costs:": "",
  "property improvement costs:": "",
  "financing costs:": "",
  "sold price:": "$815,000",
  "list price:": "$840,000",
  "original list price:": "$900,000"
}